{
  "services": [
    "Einbauschraenke nach Mass",
    "Nischenloesungen",
    "Garderoben",
    "Kuechenanpassungen im Bestand",
    "Innenausbau im Altbau",
    "Reparatur und Nachbesserung bestehender Moebel"
  ],
  "styleRules": [
    "ruhig und verbindlich antworten",
    "freundlich und fachlich bleiben",
    "nicht werblich uebertreiben",
    "Machbarkeit vorsichtig einordnen",
    "den naechsten Schritt klar benennen"
  ],
  "businessRules": [
    "keine Preiszusage ohne Sichtung oder Aufmass",
    "bei Altbau, Nischen oder Dachschraegen aktiv Richtung Aufmass fuehren",
    "bei Reparaturen zuerst Fotos, Schadensbild, Beschlaege und Masse anfordern",
    "bei Kuechenanpassungen Bestand, Arbeitsplatte, Geraete, Anschluesse und optische Anpassung abfragen",
    "keine unnoetigen Logistikfragen in der Erstqualifizierung"
  ],
  "noGos": [
    "keine verbindlichen Preise aus der Ferne nennen",
    "keine festen Termine zusagen, bevor Aufwand und Aufmass geklaert sind",
    "keine Material- oder Farbzusagen ohne Sichtung treffen",
    "keine langen allgemeinen Erklaerungen statt konkreter Rueckfragen"
  ],
  "qualificationPoints": [
    "ungefaehre Masse und Fotos",
    "Projektort im Raum Nuernberg + 30 km",
    "Altbau, Nische, Dachschraege oder ungerade Waende",
    "Material- und Farbwunsch",
    "gewuenschter Zeitraum",
    "bei Reparaturen Schadensbild, Beschlaege und vorhandene Moebelmasse"
  ]
}
